bit/__init__.py
bit/controller.py
bit/message.py
bit/middleware.py
bit/model.py
bit/protocol.py
bit/py.typed
bit/type/__init__.py
bit/type/base.py
bit/type/bitarray.py
bit/type/endian.py
bit/type/integer.py
bit/type/network.py
bit/type/string.py
bit_common-0.1.15.dist-info/METADATA
bit_common-0.1.15.dist-info/WHEEL
bit_common-0.1.15.dist-info/RECORD
