Metadata-Version: 2.1
Name: bit-common
Version: 0.1.15
Summary: Bit common types and utilities.
License: MIT
Author: Yury Sokov
Author-email: me@yurzs.dev
Requires-Python: >=3.12,<4.0
Classifier: License :: OSI Approved :: MIT License
Classifier: Programming Language :: Python :: 3
Classifier: Programming Language :: Python :: 3.12
Requires-Dist: pydantic (>=2.6.4,<3.0.0)
